{"pageContext":{"notebook":"React-web","section":"React.js[실습]","page":{"id":"0-cccf785c57647748ba544a7edeb3f940!1-BC575AB8E2AB9833!2147","self":"https://www.onenote.com/api/v1.0/me/notes/pages/0-cccf785c57647748ba544a7edeb3f940!1-BC575AB8E2AB9833!2147","createdTime":"2018-05-02T03:58:45.554Z","title":"DOM의 height 파악하기","createdByAppId":"","links":{"oneNoteEmbedUrl":{"href":"https://onedrive.live.com/redir.aspx?cid=bc575ab8e2ab9833&page=edit&resid=BC575AB8E2AB9833!2142&parId=BC575AB8E2AB9833!109&wd=target%28React.js%5B%EC%8B%A4%EC%8A%B5%5D.one%7C3645fdc8-397e-b34c-bee1-c170258420bb%2FDOM%EC%9D%98%20height%20%ED%8C%8C%EC%95%85%ED%95%98%EA%B8%B0%7C0b55e4a5-5d49-a346-bd78-c40cb4c5cf76%2F%29"},"oneNoteClientUrl":{"href":"onenote:https://d.docs.live.net/bc575ab8e2ab9833/Documents/React-web/React.js%5B%EC%8B%A4%EC%8A%B5%5D.one#DOM%EC%9D%98%20height%20%ED%8C%8C%EC%95%85%ED%95%98%EA%B8%B0&section-id=3645fdc8-397e-b34c-bee1-c170258420bb&page-id=0b55e4a5-5d49-a346-bd78-c40cb4c5cf76&end"},"oneNoteWebUrl":{"href":"https://onedrive.live.com/redir.aspx?cid=bc575ab8e2ab9833&page=edit&resid=BC575AB8E2AB9833!2142&parId=BC575AB8E2AB9833!109&wd=target%28React.js%5B%EC%8B%A4%EC%8A%B5%5D.one%7C3645fdc8-397e-b34c-bee1-c170258420bb%2FDOM%EC%9D%98%20height%20%ED%8C%8C%EC%95%85%ED%95%98%EA%B8%B0%7C0b55e4a5-5d49-a346-bd78-c40cb4c5cf76%2F%29"}},"contentUrl":"https://www.onenote.com/api/v1.0/me/notes/pages/0-cccf785c57647748ba544a7edeb3f940!1-BC575AB8E2AB9833!2147/content","lastModifiedTime":"2018-05-02T03:58:53Z","parentSection@odata.context":"https://www.onenote.com/api/v1.0/$metadata#me/notes/sections('0-BC575AB8E2AB9833%212147')/pages('0-cccf785c57647748ba544a7edeb3f940%211-BC575AB8E2AB9833%212147')/parentSection(id,name,self)/$entity","parentSection":{"id":"0-BC575AB8E2AB9833!2147","name":"React.js[실습]","self":"https://www.onenote.com/api/v1.0/me/notes/sections/0-BC575AB8E2AB9833!2147"},"content":"       <div ref={(elem) => this.elemHeight = elem.clientHeight}/>       ","html":"\n\t\t<div style=\"position:absolute;left:48px;top:139px;width:624px\">\n\t\t\t<p lang=\"ko-KR\" style=\"margin-top:0pt;margin-bottom:0pt\"><span style=\"font-family:Malgun Gothic\">&lt;div ref={(elem) =&gt; this.elemHeight = elem.clientHeight}/&gt;</span></p>\n\t\t</div>\n\t\n\n"}}}