{"pageContext":{"isCreatedByStatefulCreatePages":false,"notebook":"React-Native","section":"ReactNative-meetup","page":{"id":"0-1410ad7baddfa44cace148f57889a156!1-BC575AB8E2AB9833!2159","self":"https://www.onenote.com/api/v1.0/me/notes/pages/0-1410ad7baddfa44cace148f57889a156!1-BC575AB8E2AB9833!2159","createdTime":"2018-05-08T11:39:12.781Z","title":"mongoDB 호스팅","createdByAppId":"","links":{"oneNoteEmbedUrl":{"href":"https://onedrive.live.com/redir.aspx?cid=bc575ab8e2ab9833&page=edit&resid=BC575AB8E2AB9833!2149&parId=BC575AB8E2AB9833!109&wd=target%28ReactNative-meetup.one%7C9492e609-54a6-fc46-af8a-4423a720ea60%2FmongoDB%20%ED%98%B8%EC%8A%A4%ED%8C%85%7C4f42dd93-4f17-7743-9f8b-7285760e9fc9%2F%29"},"oneNoteClientUrl":{"href":"onenote:https://d.docs.live.net/bc575ab8e2ab9833/Documents/React-Native/ReactNative-meetup.one#mongoDB%20%ED%98%B8%EC%8A%A4%ED%8C%85&section-id=9492e609-54a6-fc46-af8a-4423a720ea60&page-id=4f42dd93-4f17-7743-9f8b-7285760e9fc9&end"},"oneNoteWebUrl":{"href":"https://onedrive.live.com/redir.aspx?cid=bc575ab8e2ab9833&page=edit&resid=BC575AB8E2AB9833!2149&parId=BC575AB8E2AB9833!109&wd=target%28ReactNative-meetup.one%7C9492e609-54a6-fc46-af8a-4423a720ea60%2FmongoDB%20%ED%98%B8%EC%8A%A4%ED%8C%85%7C4f42dd93-4f17-7743-9f8b-7285760e9fc9%2F%29"}},"contentUrl":"https://www.onenote.com/api/v1.0/me/notes/pages/0-1410ad7baddfa44cace148f57889a156!1-BC575AB8E2AB9833!2159/content","lastModifiedTime":"2018-05-08T11:40:15Z","parentSection@odata.context":"https://www.onenote.com/api/v1.0/$metadata#me/notes/sections('0-BC575AB8E2AB9833%212159')/pages('0-1410ad7baddfa44cace148f57889a156%211-BC575AB8E2AB9833%212159')/parentSection(id,name,self)/$entity","parentSection":{"id":"0-BC575AB8E2AB9833!2159","name":"ReactNative-meetup","self":"https://www.onenote.com/api/v1.0/me/notes/sections/0-BC575AB8E2AB9833!2159"},"content":"       mLab    https://mlab.com/    AWS -> SANDBOX 선택       ","html":"\n\t\t<div style=\"position:absolute;left:48px;top:139px;width:576px\">\n\t\t\t<h2 lang=\"ko-KR\" style=\"font-size:14pt;color:#2e75b5;margin-top:0pt;margin-bottom:0pt\">mLab</h2>\n\t\t\t<p lang=\"ko-KR\" style=\"margin-top:0pt;margin-bottom:0pt\"><a href=\"https://mlab.com/\">https://mlab.com/</a></p>\n\t\t\t<p lang=\"ko-KR\" style=\"margin-top:0pt;margin-bottom:0pt\">AWS -&gt; SANDBOX <span style=\"font-family:Malgun Gothic\">&#xC120;&#xD0DD;</span></p>\n\t\t</div>\n\t\n\n"}}}