{"pageContext":{"notebook":"Database","section":"MySQL","page":{"id":"0-7c1085d4ef23180835a3265eabb48699!1-BC575AB8E2AB9833!2164","self":"https://www.onenote.com/api/v1.0/me/notes/pages/0-7c1085d4ef23180835a3265eabb48699!1-BC575AB8E2AB9833!2164","createdTime":"2018-05-09T16:33:56.284Z","title":"MySQL function모음","createdByAppId":"","links":{"oneNoteEmbedUrl":{"href":"https://onedrive.live.com/redir.aspx?cid=bc575ab8e2ab9833&page=edit&resid=BC575AB8E2AB9833!2160&parId=BC575AB8E2AB9833!109&wd=target%28MySQL.one%7C4f9f1f0f-c5af-1b45-8574-b8f105c2e0e8%2FMySQL%20function%EB%AA%A8%EC%9D%8C%7Cc72abd5c-f04b-6640-8734-c7f8c8b3502d%2F%29"},"oneNoteClientUrl":{"href":"onenote:https://d.docs.live.net/bc575ab8e2ab9833/Documents/Database/MySQL.one#MySQL%20function%EB%AA%A8%EC%9D%8C&section-id=4f9f1f0f-c5af-1b45-8574-b8f105c2e0e8&page-id=c72abd5c-f04b-6640-8734-c7f8c8b3502d&end"},"oneNoteWebUrl":{"href":"https://onedrive.live.com/redir.aspx?cid=bc575ab8e2ab9833&page=edit&resid=BC575AB8E2AB9833!2160&parId=BC575AB8E2AB9833!109&wd=target%28MySQL.one%7C4f9f1f0f-c5af-1b45-8574-b8f105c2e0e8%2FMySQL%20function%EB%AA%A8%EC%9D%8C%7Cc72abd5c-f04b-6640-8734-c7f8c8b3502d%2F%29"}},"contentUrl":"https://www.onenote.com/api/v1.0/me/notes/pages/0-7c1085d4ef23180835a3265eabb48699!1-BC575AB8E2AB9833!2164/content","lastModifiedTime":"2018-05-09T16:34:07Z","parentSection@odata.context":"https://www.onenote.com/api/v1.0/$metadata#me/notes/sections('0-BC575AB8E2AB9833%212164')/pages('0-7c1085d4ef23180835a3265eabb48699%211-BC575AB8E2AB9833%212164')/parentSection(id,name,self)/$entity","parentSection":{"id":"0-BC575AB8E2AB9833!2164","name":"MySQL","self":"https://www.onenote.com/api/v1.0/me/notes/sections/0-BC575AB8E2AB9833!2164"},"content":"       W3schools    https://www.w3schools.com/sql/sql_ref_mysql.asp       ","html":"\n\t\t<div style=\"position:absolute;left:48px;top:115px;width:576px\">\n\t\t\t<h2 lang=\"ko-KR\" style=\"font-size:14pt;color:#2e75b5;margin-top:0pt;margin-bottom:0pt\">W3schools</h2>\n\t\t\t<p style=\"margin-top:0pt;margin-bottom:0pt\"><a href=\"https://www.w3schools.com/sql/sql_ref_mysql.asp\">https://www.w3schools.com/sql/sql_ref_mysql.asp</a></p>\n\t\t</div>\n\t\n\n"}}}