{"pageContext":{"notebook":"AWS","section":"AWS Lambda","page":{"id":"0-8b1da1d8f26e734b8e51b656a5dcc9a5!1-BC575AB8E2AB9833!2098","self":"https://www.onenote.com/api/v1.0/me/notes/pages/0-8b1da1d8f26e734b8e51b656a5dcc9a5!1-BC575AB8E2AB9833!2098","createdTime":"2018-01-23T10:53:16.788Z","title":"AWS Step Functions","createdByAppId":"","links":{"oneNoteEmbedUrl":{"href":"https://onedrive.live.com/redir.aspx?cid=bc575ab8e2ab9833&page=edit&resid=BC575AB8E2AB9833!2000&parId=BC575AB8E2AB9833!109&wd=target%28AWS%20Lambda.one%7C01064184-321d-f845-a242-b424116ecdf9%2FAWS%20Step%20Functions%7C1d13c25c-26ad-aa4f-843b-63ba00e73137%2F%29"},"oneNoteClientUrl":{"href":"onenote:https://d.docs.live.net/bc575ab8e2ab9833/Documents/AWS/AWS%20Lambda.one#AWS%20Step%20Functions&section-id=01064184-321d-f845-a242-b424116ecdf9&page-id=1d13c25c-26ad-aa4f-843b-63ba00e73137&end"},"oneNoteWebUrl":{"href":"https://onedrive.live.com/redir.aspx?cid=bc575ab8e2ab9833&page=edit&resid=BC575AB8E2AB9833!2000&parId=BC575AB8E2AB9833!109&wd=target%28AWS%20Lambda.one%7C01064184-321d-f845-a242-b424116ecdf9%2FAWS%20Step%20Functions%7C1d13c25c-26ad-aa4f-843b-63ba00e73137%2F%29"}},"contentUrl":"https://www.onenote.com/api/v1.0/me/notes/pages/0-8b1da1d8f26e734b8e51b656a5dcc9a5!1-BC575AB8E2AB9833!2098/content","lastModifiedTime":"2018-03-30T12:36:27Z","parentSection@odata.context":"https://www.onenote.com/api/v1.0/$metadata#me/notes/sections('0-BC575AB8E2AB9833%212098')/pages('0-8b1da1d8f26e734b8e51b656a5dcc9a5%211-BC575AB8E2AB9833%212098')/parentSection(id,name,self)/$entity","parentSection":{"id":"0-BC575AB8E2AB9833!2098","name":"AWS Lambda","self":"https://www.onenote.com/api/v1.0/me/notes/sections/0-BC575AB8E2AB9833!2098"},"content":"  ","html":"\n\n"}}}